gomaps/__init__.py
gomaps/gmapss.py
gomaps/utils.py
gomaps-0.3.6.dist-info/LICENSE
gomaps-0.3.6.dist-info/METADATA
gomaps-0.3.6.dist-info/WHEEL
gomaps-0.3.6.dist-info/top_level.txt
gomaps-0.3.6.dist-info/RECORD
