Metadata-Version: 2.1
Name: gomaps
Version: 0.3.6
Summary: A Google Maps web scraper that gets place data based on a search
Home-page: https://github.com/jakeee51/gomaps
Author: David J. Morfe
Author-email: morphetech@gmail.com
License: MIT
Classifier: Programming Language :: Python :: 3
Classifier: License :: OSI Approved :: MIT License
Classifier: Operating System :: OS Independent
License-File: LICENSE
Requires-Dist: requests-html
Requires-Dist: pyppdf
Requires-Dist: GeoLiberator
